intrinio_sdk/__init__.py
intrinio_sdk/api_client.py
intrinio_sdk/configuration.py
intrinio_sdk/rest.py
intrinio_sdk/api/__init__.py
intrinio_sdk/api/bulk_downloads_api.py
intrinio_sdk/api/company_api.py
intrinio_sdk/api/data_point_api.py
intrinio_sdk/api/data_tag_api.py
intrinio_sdk/api/esg_api.py
intrinio_sdk/api/et_fs_api.py
intrinio_sdk/api/filing_api.py
intrinio_sdk/api/forex_api.py
intrinio_sdk/api/fundamentals_api.py
intrinio_sdk/api/historical_data_api.py
intrinio_sdk/api/index_api.py
intrinio_sdk/api/insider_transaction_filings_api.py
intrinio_sdk/api/market_api.py
intrinio_sdk/api/municipality_api.py
intrinio_sdk/api/options_api.py
intrinio_sdk/api/owners_api.py
intrinio_sdk/api/security_api.py
intrinio_sdk/api/stock_exchange_api.py
intrinio_sdk/api/technical_api.py
intrinio_sdk/api/zacks_api.py
intrinio_sdk/models/__init__.py
intrinio_sdk/models/accumulation_distribution_index_technical_value.py
intrinio_sdk/models/api_response_bulk_download_links.py
intrinio_sdk/models/api_response_companies.py
intrinio_sdk/models/api_response_companies_search.py
intrinio_sdk/models/api_response_company_answers.py
intrinio_sdk/models/api_response_company_daily_metrics.py
intrinio_sdk/models/api_response_company_filings.py
intrinio_sdk/models/api_response_company_fundamentals.py
intrinio_sdk/models/api_response_company_historical_data.py
intrinio_sdk/models/api_response_company_insider_transaction_filings.py
intrinio_sdk/models/api_response_company_news.py
intrinio_sdk/models/api_response_company_news_body.py
intrinio_sdk/models/api_response_company_public_float_result.py
intrinio_sdk/models/api_response_company_recognize.py
intrinio_sdk/models/api_response_company_securities.py
intrinio_sdk/models/api_response_company_shares_outstanding.py
intrinio_sdk/models/api_response_data_tags.py
intrinio_sdk/models/api_response_data_tags_search.py
intrinio_sdk/models/api_response_economic_index_historical_data.py
intrinio_sdk/models/api_response_economic_indices.py
intrinio_sdk-6.42.0.dist-info/METADATA
intrinio_sdk-6.42.0.dist-info/WHEEL
intrinio_sdk-6.42.0.dist-info/top_level.txt
intrinio_sdk-6.42.0.dist-info/RECORD
