Metadata-Version: 2.4
Name: intrinio-sdk
Version: 6.42.0
Summary: Intrinio API
Home-page: https://github.com/intrinio/python-sdk
Author-email: 
Keywords: Swagger,Intrinio API
Requires-Dist: urllib3>=1.15
Requires-Dist: six>=1.10
Requires-Dist: certifi
Requires-Dist: python-dateutil
Requires-Dist: retrying>=1.3.3
Dynamic: description
Dynamic: home-page
Dynamic: keywords
Dynamic: requires-dist
Dynamic: summary
